self_supervised_dermatology/__init__.py
self_supervised_dermatology/eval_downstream.py
self_supervised_dermatology/knn_figs.py
self_supervised_dermatology/test_dataset_shift.py
self_supervised_dermatology/train_byol.py
self_supervised_dermatology/train_colorme.py
self_supervised_dermatology/train_dino.py
self_supervised_dermatology/train_ibot.py
self_supervised_dermatology/train_simclr.py
self_supervised_dermatology/augmentations/__init__.py
self_supervised_dermatology/augmentations/augmentations.py
self_supervised_dermatology/augmentations/dino.py
self_supervised_dermatology/augmentations/ibot.py
self_supervised_dermatology/augmentations/simclr.py
self_supervised_dermatology/datasets/__init__.py
self_supervised_dermatology/datasets/encrypted_image_folder.py
self_supervised_dermatology/datasets/utils.py
self_supervised_dermatology/datasets/downstream/__init__.py
self_supervised_dermatology/datasets/downstream/base_dataset.py
self_supervised_dermatology/datasets/downstream/fitzpatrick17_dataset.py
self_supervised_dermatology/datasets/downstream/ham10000_dataset.py
self_supervised_dermatology/datasets/downstream/isic_task1_dataset.py
self_supervised_dermatology/datasets/downstream/pad_ufes_20_dataset.py
self_supervised_dermatology/datasets/wrappers/__init__.py
self_supervised_dermatology/datasets/wrappers/base_wrapper.py
self_supervised_dermatology/datasets/wrappers/colorme_wrapper.py
self_supervised_dermatology/datasets/wrappers/ibot_wrapper.py
self_supervised_dermatology/distributed/__init__.py
self_supervised_dermatology/distributed/distributed.py
self_supervised_dermatology/distributed/launch.py
self_supervised_dermatology/losses/__init__.py
self_supervised_dermatology/losses/dino_loss.py
self_supervised_dermatology/losses/distance_loss.py
self_supervised_dermatology/losses/ibot_loss.py
self_supervised_dermatology/losses/nt_xent.py
self_supervised_dermatology/models/__init__.py
self_supervised_dermatology/models/classifiers.py
self_supervised_dermatology-0.0.16.dist-info/METADATA
self_supervised_dermatology-0.0.16.dist-info/WHEEL
self_supervised_dermatology-0.0.16.dist-info/top_level.txt
self_supervised_dermatology-0.0.16.dist-info/RECORD
