Metadata-Version: 2.1
Name: self-supervised-dermatology
Version: 0.0.16
Summary: Unsupervised Pre-Training for Texture Segmentation in Dermatology
Home-page: https://github.com/FabianGroeger96/
Author: Fabian Groeger
Author-email: fabian.groeger@hslu.ch
License: UNKNOWN
Platform: UNKNOWN
Classifier: Programming Language :: Python :: 3
Classifier: Operating System :: OS Independent
Requires-Python: >=3.6
Requires-Dist: torch
Requires-Dist: einops
Requires-Dist: segmentation-models-pytorch
